exe2txt/__init__.py
exe2txt/cli.py
exe2txt/core.py
exe2txt/py.typed
exe2txt-0.1.0.dist-info/METADATA
exe2txt-0.1.0.dist-info/WHEEL
exe2txt-0.1.0.dist-info/entry_points.txt
exe2txt-0.1.0.dist-info/licenses/LICENSE
exe2txt-0.1.0.dist-info/RECORD
