Metadata-Version: 2.4
Name: exe2txt
Version: 0.1.0
Summary: Convert Windows EXE/DLL files into text representations for LLM prompting.
Project-URL: Homepage, https://github.com/crlotwhite/exe2txt
Project-URL: Repository, https://github.com/crlotwhite/exe2txt
Project-URL: Issues, https://github.com/crlotwhite/exe2txt/issues
Author-email: Noel Kim <crlotwhite@gmail.com>
License-Expression: MIT
License-File: LICENSE
Keywords: dll,exe,llm,pe,reverse-engineering,windows
Classifier: Development Status :: 3 - Alpha
Classifier: Intended Audience :: Developers
Classifier: License :: OSI Approved :: MIT License
Classifier: Programming Language :: Python :: 3
Classifier: Programming Language :: Python :: 3.10
Classifier: Programming Language :: Python :: 3.11
Classifier: Programming Language :: Python :: 3.12
Classifier: Programming Language :: Python :: 3.13
Classifier: Topic :: Security
Classifier: Topic :: Software Development :: Disassemblers
Classifier: Topic :: Utilities
Classifier: Typing :: Typed
Requires-Python: >=3.10
Requires-Dist: pefile>=2023.2.7
Provides-Extra: dev
Requires-Dist: mypy>=1.13.0; extra == 'dev'
Requires-Dist: pytest-cov>=4.0.0; extra == 'dev'
Requires-Dist: pytest>=8.0.0; extra == 'dev'
Requires-Dist: ruff>=0.8.0; extra == 'dev'
